icevision_dashboard/__init__.py
icevision_dashboard/_nbdev.py
icevision_dashboard/components.py
icevision_dashboard/dashboards.py
icevision_dashboard/utils.py
icevision_dashboards/__init__.py
icevision_dashboards/_nbdev.py
icevision_dashboards/dashboards.py
icevision_dashboards/data.py
icevision_dashboards/metrics.py
icevision_dashboards/utils.py
icevision_dashboards/core/__init__.py
icevision_dashboards/core/dashboards.py
icevision_dashboards/core/data.py
icevision_dashboards/plotting/__init__.py
icevision_dashboards/plotting/controls.py
icevision_dashboards/plotting/core.py
icevision_dashboards/plotting/utils.py
icevision_dashboards-0.0.8.dist-info/LICENSE
icevision_dashboards-0.0.8.dist-info/METADATA
icevision_dashboards-0.0.8.dist-info/WHEEL
icevision_dashboards-0.0.8.dist-info/entry_points.txt
icevision_dashboards-0.0.8.dist-info/top_level.txt
icevision_dashboards-0.0.8.dist-info/RECORD
