Metadata-Version: 2.1
Name: icevision-dashboards
Version: 0.0.8
Summary: Provides dashboard components and dashboards to get insight into data.
Home-page: https://github.com/fstroth/icevision_dashboards/tree/master/
Author: Frederik Strothmann
Author-email: frstrothmann@gmail.com
License: Apache Software License 2.0
Keywords: machine learning,dashboard,deep learning
Platform: UNKNOWN
Classifier: Development Status :: 3 - Alpha
Classifier: Intended Audience :: Developers
Classifier: License :: OSI Approved :: Apache Software License
Classifier: Natural Language :: English
Classifier: Programming Language :: Python :: 3.7
Classifier: Programming Language :: Python :: 3.8
Requires-Python: >=3.7
Requires-Dist: bokeh
Requires-Dist: panel
Requires-Dist: pandas
Requires-Dist: numpy
Requires-Dist: icevision[all] (>=0.12.0)
Requires-Dist: fastprogress
Requires-Dist: scikit-learn
Requires-Dist: joblib
Requires-Dist: icedata (==0.5.1)
Requires-Dist: pytest
